setup.py
v02_distributions/Binomialdistribution.py
v02_distributions/Gaussiandistribution.py
v02_distributions/Generaldistribution.py
v02_distributions/__init__.py
v02_distributions.egg-info/PKG-INFO
v02_distributions.egg-info/SOURCES.txt
v02_distributions.egg-info/dependency_links.txt
v02_distributions.egg-info/not-zip-safe
v02_distributions.egg-info/top_level.txt